pyspark_uploader/__init__.py
pyspark_uploader/udf.py
pyspark_uploader-0.1.2.dist-info/DESCRIPTION.rst
pyspark_uploader-0.1.2.dist-info/METADATA
pyspark_uploader-0.1.2.dist-info/RECORD
pyspark_uploader-0.1.2.dist-info/WHEEL
pyspark_uploader-0.1.2.dist-info/metadata.json
pyspark_uploader-0.1.2.dist-info/top_level.txt
