Metadata-Version: 2.0
Name: pyspark-uploader
Version: 0.1.2
Summary: Enables rapid development of packages to be used via PySpark on a Spark cluster by uploading a local Python package to the cluster.
Home-page: UNKNOWN
Author: Scott Hajek
Author-email: scott.hajek@alumni.unc.edu
License: UNKNOWN
Platform: UNKNOWN
